COPYING.TXT
Changelog
INSTALL.TXT
LICENSE.TXT
MANIFEST.in
README.md
mkdocs.yml
release_info.txt
requirements.txt
setup.cfg
setup.py
technical_details.txt
docs/3d-view.md
docs/ParameterGroup.dia
docs/articles.md
docs/bounding-box.md
docs/cli-examples.md
docs/developers-guide.md
docs/engrave-fonts.md
docs/faq.md
docs/features.md
docs/getting-started.md
docs/index.md
docs/installation-macos.md
docs/installation.md
docs/introduction.md
docs/keyboard-shortcuts.md
docs/main-page.md
docs/menu-items.md
docs/model-transformations.md
docs/modeling-inkscape-svg.md
docs/modeling-openscad-dxf.md
docs/opengl-troubles.md
docs/other-programs.md
docs/parallel-processing.md
docs/process-settings.md
docs/release-notes.md
docs/requirements.md
docs/screenshots.md
docs/server-mode.md
docs/supported-formats.md
docs/task-settings.md
docs/tool-types.md
docs/touch-off.md
docs/video-translations.md
docs/img/2d-modeling-polygon_directions.png
docs/img/2d-modeling-polygon_directions.svg
docs/img/2d-multilayer-engrave-model.png
docs/img/2d-multilayer-engrave-toolpath.png
docs/img/2d-multilayer-engrave.png
docs/img/2d-multilayer-engrave.svg
docs/img/3d-view-context-menu.png
docs/img/3d-view-visible-items.png
docs/img/3d-view.png
docs/img/engrave-font-courier.png
docs/img/engrave-font-cursive.png
docs/img/engrave-font-cyrillic2.png
docs/img/engrave-font-gothic-british.png
docs/img/engrave-font-gothic-german.png
docs/img/engrave-font-gothic-italian.png
docs/img/engrave-font-greek-complex-small.png
docs/img/engrave-font-greek-complex.png
docs/img/engrave-font-greek-ol-plus.png
docs/img/engrave-font-greek-ol.png
docs/img/engrave-font-greek-plain.png
docs/img/engrave-font-greek-simplex.png
docs/img/engrave-font-iso8859-11.png
docs/img/engrave-font-italian-complex-small.png
docs/img/engrave-font-italian-complex.png
docs/img/engrave-font-italian-triplex.png
docs/img/engrave-font-japanese.png
docs/img/engrave-font-kochi-gothic.png
docs/img/engrave-font-kochi-mincho.png
pycam.egg-info/PKG-INFO
pycam.egg-info/SOURCES.txt
pycam.egg-info/dependency_links.txt
pycam.egg-info/top_level.txt
